connectbox_exporter/__init__.py
connectbox_exporter/config.py
connectbox_exporter/connectbox_exporter.py
connectbox_exporter/logger.py
connectbox_exporter/xml2metric.py
connectbox_prometheus-0.2.10.dist-info/LICENSE
connectbox_prometheus-0.2.10.dist-info/METADATA
connectbox_prometheus-0.2.10.dist-info/WHEEL
connectbox_prometheus-0.2.10.dist-info/entry_points.txt
connectbox_prometheus-0.2.10.dist-info/top_level.txt
connectbox_prometheus-0.2.10.dist-info/RECORD
