Metadata-Version: 2.1
Name: connectbox-prometheus
Version: 0.2.10
Summary: Prometheus exporter for Compal CH7465LG cable modems, commonly sold as "Connect Box"
Home-page: https://github.com/mbugert/connectbox-prometheus
Author: Michael Bugert
Author-email: git@mbugert.de
License: UNKNOWN
Platform: UNKNOWN
Classifier: Development Status :: 5 - Production/Stable
Classifier: Intended Audience :: System Administrators
Classifier: License :: OSI Approved :: Apache Software License
Classifier: Programming Language :: Python :: 3.7
Classifier: Programming Language :: Python :: 3.8
Classifier: Programming Language :: Python :: 3.9
Classifier: Topic :: System :: Networking :: Monitoring
Requires-Python: >=3.7
Requires-Dist: click (==7.1.2)
Requires-Dist: compal (==0.3.1)
Requires-Dist: deepmerge (==0.2.1)
Requires-Dist: lxml (>=4.5.0)
Requires-Dist: prometheus-client (==0.9.0)
Requires-Dist: ruamel.yaml (==0.16.13)
